setup.cfg
setup.py
anmolpant_dist_package/Binomialdistribution.py
anmolpant_dist_package/Gaussiandistribution.py
anmolpant_dist_package/Generaldistribution.py
anmolpant_dist_package/__init__.py
anmolpant_dist_package.egg-info/PKG-INFO
anmolpant_dist_package.egg-info/SOURCES.txt
anmolpant_dist_package.egg-info/dependency_links.txt
anmolpant_dist_package.egg-info/not-zip-safe
anmolpant_dist_package.egg-info/top_level.txt